{
  "background": "Background2.png",
  "nextMap": "Level1",
  "nextMapPath": "map/Level1.json",
  "mapSpeed": 500,
  "tiles": [
      {"type": "GrassWinter", "y": 0, "zoom": 2},
      {"type": "GrassWinter", "y": 0, "zoom": 2},
      {"type": "GrassWinter", "y": 0, "zoom": 2},
      {"type": "GrassWinter", "y": 0, "zoom": 2},
      {"type": "GrassWinter", "y": 0, "zoom": 2},
      {"type": "GrassWinter", "y": 0, "zoom": 2},
      {"type": "null",  "y": 0, "zoom": 2},
      {"type": "GrassWinter", "y": 0, "zoom": 2},
      {"type": "GrassWinter", "y": 0, "zoom": 2},
      {"type": "GrassWinter", "y": 0, "zoom": 2},
      {"type": "GrassWinter", "y": 0, "zoom": 2},
      {"type": "null",  "y": 0, "zoom": 2},
      {"type": "null",  "y": 0, "zoom": 2},
      {"type": "GrassWinter", "y": 0, "zoom": 2},
      {"type": "GrassWinter", "y": 0, "zoom": 2},
      {"type": "GrassWinter", "y": 0, "zoom": 2},
      {"type": "GrassWinter", "y": 0, "zoom": 2},
      {"type": "GrassWinter", "y": 0, "zoom": 2},
      {"type": "null",  "y": 0, "zoom": 2},
      {"type": "null",  "y": 0, "zoom": 2},
      {"type": "GrassWinter", "y": 64, "zoom": 2},
      {"type": "GrassWinter", "y": 64, "zoom": 2},
      {"type": "GrassWinter", "y": 64, "zoom": 2},
      {"type": "GrassWinter", "y": 64, "zoom": 2},
      {"type": "GrassWinter", "y": 64, "zoom": 2},
      {"type": "null",  "y": 64, "zoom": 2},
      {"type": "null",  "y": 64, "zoom": 2},
      {"type": "GrassWinter", "y": 128, "zoom": 2},
      {"type": "GrassWinter", "y": 128, "zoom": 2},
      {"type": "GrassWinter", "y": 128, "zoom": 2},
      {"type": "GrassWinter", "y": 128, "zoom": 2},
      {"type": "GrassWinter", "y": 128, "zoom": 2},
      {"type": "GrassWinter", "y": 128, "zoom": 2},
      {"type": "null",  "y": 128, "zoom": 2},
      {"type": "GrassWinter", "y": 0, "zoom": 2},
      {"type": "GrassWinter", "y": 0, "zoom": 2},
      {"type": "GrassWinter", "y": 0, "zoom": 2},
      {"type": "GrassWinter", "y": 0, "zoom": 2},
      {"type": "GrassWinter", "y": 0, "zoom": 2},
      {"type": "null",  "y": 0, "zoom": 2},
      {"type": "null",  "y": 0, "zoom": 2},
      {"type": "GrassWinter", "y": 0, "zoom": 2},
      {"type": "GrassWinter", "y": 0, "zoom": 2}
    ]
}
